smallants_mcp_pypi/__init__.py
smallants_mcp_pypi-0.1.1.dist-info/METADATA
smallants_mcp_pypi-0.1.1.dist-info/WHEEL
smallants_mcp_pypi-0.1.1.dist-info/entry_points.txt
smallants_mcp_pypi-0.1.1.dist-info/RECORD
