Metadata-Version: 2.4
Name: smallants-mcp-pypi
Version: 0.1.1
Summary: Add your description here
Author-email: liruijiang <2970053530@qq.com>
Requires-Python: >=3.13
Requires-Dist: mcp[cli]>=1.13.0
